{"cameraMode":{"drawMode":0,"name":"Shaded","section":"Shading Mode"},"sceneLighting":true,"audioPlay":false,"sceneViewState":{"m_AlwaysRefresh":false,"showFog":true,"showSkybox":true,"showFlares":true,"showImageEffects":true,"showParticleSystems":true,"showVisualEffectGraphs":true,"m_FxEnabled":true},"in2DMode":false,"pivot":{"x":11.14623737335205,"y":3.5357062816619875,"z":-1.6321086883544922},"rotation":{"x":-0.03171796724200249,"y":0.8736369609832764,"z":0.05747295171022415,"w":0.4821605384349823},"size":8.945428848266602,"orthographic":false}